Metadata-Version: 1.0
Name: dopltech-sdk
Version: 1.0.2
Summary: Dopl Technologies SDK
Home-page: https://github.com/dopl-technologies/sdk-python
Author: Ryan James
Author-email: ryan@dopltechnologies.com
License: UNKNOWN
Keywords: dopl,technologies,telerobotics,sdk,electrophysiology,medicine
Platform: UNKNOWN
